sparkflowtools/__init__.py
sparkflowtools/__main__.py
sparkflowtools/configs/sample_creation_config.json
sparkflowtools/models/__init__.py
sparkflowtools/models/cluster.py
sparkflowtools/models/db.py
sparkflowtools/models/instance_fleets.py
sparkflowtools/models/step.py
sparkflowtools/utils/__init__.py
sparkflowtools/utils/aws.py
sparkflowtools/utils/aws_lambda.py
sparkflowtools/utils/config.py
sparkflowtools/utils/dynamo_db.py
sparkflowtools/utils/emr.py
sparkflowtools/utils/s3_path_utils.py
sparkflowtools-1.4.2.dist-info/LICENSE
sparkflowtools-1.4.2.dist-info/METADATA
sparkflowtools-1.4.2.dist-info/WHEEL
sparkflowtools-1.4.2.dist-info/entry_points.txt
sparkflowtools-1.4.2.dist-info/top_level.txt
sparkflowtools-1.4.2.dist-info/RECORD
